<?xml version="1.0" encoding="UTF-8"?>

<metadata
  xmlns:xsi="http://www.w3.org/2001/XMLSchema-instance"
  xmlns:dc="http://purl.org/dc/elements/1.1/"
  xmlns:dcterms="http://purl.org/dc/terms/">
  
  <dcterms:title>
	Letter from Farrell, John William to Dyer, Frank Lewis, November 22, 1909
  </dcterms:title>
  <dcterms:date>
	1909-11-22
  </dcterms:date>
  <dcterms:creator>
  	Farrell, John William
  </dcterms:creator>
  <dcterms:contributor>
	Dyer, Frank Lewis
  </dcterms:contributor>
  <dcterms:subject>
	Kleine, Charles B; Kleine, Oscar B; Scull, George Francis; Competition and market structure; Motion picture equipment
  </dcterms:subject>   
  <dcterms:publisher>
	The Thomas Edison Papers, part of The School of Arts and Sciences at Rutgers, The State University of New Jersey
  </dcterms:publisher>
  <dcterms:source>
	Courtesy of Thomas Edison National Historical Park.
  </dcterms:source>
  <dcterms:identifier>
	CK909AAA
  </dcterms:identifier>
	<dcterms:identifier>
		TAEM 214:901
	</dcterms:identifier>
  <dcterms:isPartOf>
	[CK909] Company Records Series -- Motion Picture Patents Company -- Individuals Farrell, John W. (1908-1910)
  </dcterms:isPartOf> 
  <dcterms:isPartOf type="dcterms:URI">
	http://edison.rutgers.edu/NamesSearch/glocpage.php?gloc=CK909
  </dcterms:isPartOf>none available
</metadata>
