<?xml version="1.0" encoding="UTF-8"?>

<metadata
  xmlns:xsi="http://www.w3.org/2001/XMLSchema-instance"
  xmlns:dc="http://purl.org/dc/elements/1.1/"
  xmlns:dcterms="http://purl.org/dc/terms/">
  
  <dcterms:title>
	Letter from Dick, Herman Ernest to Mallory, Walter Seeley, June 05, 1903
  </dcterms:title>
  <dcterms:date>
	1903-06-05
  </dcterms:date>
  <dcterms:creator>
  	Dick, Herman Ernest
  </dcterms:creator>
  <dcterms:contributor>
	Mallory, Walter Seeley
  </dcterms:contributor>
  <dcterms:subject>
	Bergmann, Sigmund; Edison, Thomas Alva; Electric battery; Testing and quality control
  </dcterms:subject>   
  <dcterms:publisher>
	The Thomas Edison Papers, part of The School of Arts and Sciences at Rutgers, The State University of New Jersey
  </dcterms:publisher>
  <dcterms:source>
	Courtesy of Thomas Edison National Historical Park.
  </dcterms:source>
  <dcterms:identifier>
	D0304AAW
  </dcterms:identifier>
	<dcterms:identifier>
		TAEM 188:152
	</dcterms:identifier>
  <dcterms:isPartOf>
	[D0304] Document File Series -- 1903 (D-03-04) Battery -- Storage -- Foreign
  </dcterms:isPartOf> 
  <dcterms:isPartOf type="dcterms:URI">
	http://edison.rutgers.edu/NamesSearch/glocpage.php?gloc=D0304
  </dcterms:isPartOf>none available
</metadata>
