<?xml version="1.0" encoding="UTF-8"?>

<metadata
  xmlns:xsi="http://www.w3.org/2001/XMLSchema-instance"
  xmlns:dc="http://purl.org/dc/elements/1.1/"
  xmlns:dcterms="http://purl.org/dc/terms/">
  
  <dcterms:title>
	Letter from Dyer Edmonds and Dyer and Edmonds, Samuel Owen to Exhibition. Buffalo Pan-American (1901) and Taylor, Oscar T, June 15, 1901
  </dcterms:title>
  <dcterms:date>
	1901-06-15
  </dcterms:date>
  <dcterms:creator>
  	Dyer Edmonds and Dyer; Edmonds, Samuel Owen
  </dcterms:creator>
  <dcterms:contributor>
	Exhibition. Buffalo Pan-American (1901); Taylor, Oscar T
  </dcterms:contributor>
  <dcterms:subject>
	Edison, Thomas Alva; Lubin, Sigmund; Expositions, demonstrations, lectures; Motion picture projectors; Patent infringement
  </dcterms:subject>   
  <dcterms:publisher>
	The Thomas Edison Papers, part of The School of Arts and Sciences at Rutgers, The State University of New Jersey
  </dcterms:publisher>
  <dcterms:source>
	Courtesy of Thomas Edison National Historical Park.
  </dcterms:source>
  <dcterms:identifier>
	D0122AAE
  </dcterms:identifier>
	<dcterms:identifier>
		TAEM 187:241
	</dcterms:identifier>
  <dcterms:isPartOf>
	[D0122] Document File Series -- 1901 (D-01-22) Exhibitions
  </dcterms:isPartOf> 
  <dcterms:isPartOf type="dcterms:URI">
	http://edison.rutgers.edu/NamesSearch/glocpage.php?gloc=D0122
  </dcterms:isPartOf>none available
</metadata>
