<?xml version="1.0" encoding="UTF-8"?>

<metadata
  xmlns:xsi="http://www.w3.org/2001/XMLSchema-instance"
  xmlns:dc="http://purl.org/dc/elements/1.1/"
  xmlns:dcterms="http://purl.org/dc/terms/">
  
  <dcterms:title>
	Letter from Wilson, Carl Hillis to McChesney, Leonard Ward, September 21, 1915
  </dcterms:title>
  <dcterms:date>
	1915-09-21
  </dcterms:date>
  <dcterms:creator>
  	Wilson, Carl Hillis
  </dcterms:creator>
  <dcterms:contributor>
	McChesney, Leonard Ward
  </dcterms:contributor>
  <dcterms:subject>
	Management (companies and organizations); Motion pictures
  </dcterms:subject>   
  <dcterms:publisher>
	The Thomas Edison Papers, part of The School of Arts and Sciences at Rutgers, The State University of New Jersey
  </dcterms:publisher>
  <dcterms:source>
	Courtesy of Thomas Edison National Historical Park.
  </dcterms:source>
  <dcterms:identifier>
	CK912ABJ
  </dcterms:identifier>
	<dcterms:identifier>
		TAEM 214:1071
	</dcterms:identifier>
  <dcterms:isPartOf>
	[CK912] Company Records Series -- Motion Picture Patents Company -- General Film Company Records (1913-1915)
  </dcterms:isPartOf> 
  <dcterms:isPartOf type="dcterms:URI">
	http://edison.rutgers.edu/NamesSearch/glocpage.php?gloc=CK912
  </dcterms:isPartOf>none available
</metadata>
