<?xml version="1.0" encoding="UTF-8"?>

<metadata
  xmlns:xsi="http://www.w3.org/2001/XMLSchema-instance"
  xmlns:dc="http://purl.org/dc/elements/1.1/"
  xmlns:dcterms="http://purl.org/dc/terms/">
  
  <dcterms:title>
	Letter from Leeming, Harry Toyne to Pullin, Frederick Charles and Edison, Thomas Alva, March 18, 1915
  </dcterms:title>
  <dcterms:date>
	1915-03-18
  </dcterms:date>
  <dcterms:creator>
  	Leeming, Harry Toyne
  </dcterms:creator>
  <dcterms:contributor>
	Pullin, Frederick Charles; Edison, Thomas Alva
  </dcterms:contributor>
  <dcterms:subject>
	Eckert, Walter Lewis; Edison (Thomas A.) Inc; Heyden Chemical Works; Philips, Eugene H; Chemicals, chemical products, and chemical processes; Contracts and other legal concerns; Sales and service
  </dcterms:subject>   
  <dcterms:publisher>
	The Thomas Edison Papers, part of The School of Arts and Sciences at Rutgers, The State University of New Jersey
  </dcterms:publisher>
  <dcterms:source>
	Courtesy of Thomas Edison National Historical Park.
  </dcterms:source>
  <dcterms:identifier>
	CM01ag
  </dcterms:identifier>
	<dcterms:identifier>
		TAEM 281:278
	</dcterms:identifier>
  <dcterms:isPartOf>
	[CM01] Special Collections Series -- Chemical Production Records -- Organic Chemical Plant Records General Operations (1915-1917)
  </dcterms:isPartOf> 
  <dcterms:isPartOf type="dcterms:URI">
	http://edison.rutgers.edu/NamesSearch/glocpage.php?gloc=CM01
  </dcterms:isPartOf>none available
</metadata>
