<?xml version="1.0" encoding="UTF-8"?>

<metadata
  xmlns:xsi="http://www.w3.org/2001/XMLSchema-instance"
  xmlns:dc="http://purl.org/dc/elements/1.1/"
  xmlns:dcterms="http://purl.org/dc/terms/">
  
  <dcterms:title>
	Letter from Kleine, George to Edison (Thomas A.) Inc, September 28, 1916
  </dcterms:title>
  <dcterms:date>
	1916-09-28
  </dcterms:date>
  <dcterms:creator>
  	Kleine, George
  </dcterms:creator>
  <dcterms:contributor>
	Edison (Thomas A.) Inc
  </dcterms:contributor>
  <dcterms:subject>
	McChesney, Leonard Ward; Wilson, Carl Hillis; Competition and market structure; Financial operations (companies and organizations); Sales and service
  </dcterms:subject>   
  <dcterms:publisher>
	The Thomas Edison Papers, part of The School of Arts and Sciences at Rutgers, The State University of New Jersey
  </dcterms:publisher>
  <dcterms:source>
	Courtesy of Thomas Edison National Historical Park.
  </dcterms:source>
  <dcterms:identifier>
	CK913AAJ
  </dcterms:identifier>
	<dcterms:identifier>
		TAEM 214:1086
	</dcterms:identifier>
  <dcterms:isPartOf>
	[CK913] Company Records Series -- Motion Picture Patents Company -- General Film Company Records (1916)
  </dcterms:isPartOf> 
  <dcterms:isPartOf type="dcterms:URI">
	http://edison.rutgers.edu/NamesSearch/glocpage.php?gloc=CK913
  </dcterms:isPartOf>none available
</metadata>
