<?xml version="1.0" encoding="UTF-8"?>

<metadata
  xmlns:xsi="http://www.w3.org/2001/XMLSchema-instance"
  xmlns:dc="http://purl.org/dc/elements/1.1/"
  xmlns:dcterms="http://purl.org/dc/terms/">
  
  <dcterms:title>
	Letter from Bacigalupi, Peter to Gilmore, William Edgar, July 15, 1902
  </dcterms:title>
  <dcterms:date>
	1902-07-15
  </dcterms:date>
  <dcterms:creator>
  	Bacigalupi, Peter
  </dcterms:creator>
  <dcterms:contributor>
	Gilmore, William Edgar
  </dcterms:contributor>
  <dcterms:subject>
	Financial operations (companies and organizations); Sales and service; Shipping and materials handling
  </dcterms:subject>   
  <dcterms:publisher>
	The Thomas Edison Papers, part of The School of Arts and Sciences at Rutgers, The State University of New Jersey
  </dcterms:publisher>
  <dcterms:source>
	Courtesy of Thomas Edison National Historical Park.
  </dcterms:source>
  <dcterms:identifier>
	CL205ABA
  </dcterms:identifier>
	<dcterms:identifier>
		TAEM 215:657
	</dcterms:identifier>
  <dcterms:isPartOf>
	[CL205] Company Records Series -- National Phonograph Company -- Correspondence Domestic (1902)
  </dcterms:isPartOf> 
  <dcterms:isPartOf type="dcterms:URI">
	http://edison.rutgers.edu/NamesSearch/glocpage.php?gloc=CL205
  </dcterms:isPartOf>none available
</metadata>
