<?xml version="1.0" encoding="UTF-8"?>

<metadata
  xmlns:xsi="http://www.w3.org/2001/XMLSchema-instance"
  xmlns:dc="http://purl.org/dc/elements/1.1/"
  xmlns:dcterms="http://purl.org/dc/terms/">
  
  <dcterms:title>
	Letter from Sibley Quarry Co to Herter, Emil, December 05, 1907
  </dcterms:title>
  <dcterms:date>
	1907-12-05
  </dcterms:date>
  <dcterms:creator>
  	Sibley Quarry Co
  </dcterms:creator>
  <dcterms:contributor>
	Herter, Emil
  </dcterms:contributor>
  <dcterms:subject>
	Edison, Thomas Alva; West Orange Laboratory; Rolls and crushers
  </dcterms:subject>   
  <dcterms:publisher>
	The Thomas Edison Papers, part of The School of Arts and Sciences at Rutgers, The State University of New Jersey
  </dcterms:publisher>
  <dcterms:source>
	Courtesy of Thomas Edison National Historical Park.
  </dcterms:source>
  <dcterms:identifier>
	D0725AAL
  </dcterms:identifier>
	<dcterms:identifier>
		TAEM 191:544
	</dcterms:identifier>
  <dcterms:isPartOf>
	[D0725] Document File Series -- 1907 (D-07-25) Mining -- General
  </dcterms:isPartOf> 
  <dcterms:isPartOf type="dcterms:URI">
	http://edison.rutgers.edu/NamesSearch/glocpage.php?gloc=D0725
  </dcterms:isPartOf>none available
</metadata>
