<?xml version="1.0" encoding="UTF-8"?>

<metadata
  xmlns:xsi="http://www.w3.org/2001/XMLSchema-instance"
  xmlns:dc="http://purl.org/dc/elements/1.1/"
  xmlns:dcterms="http://purl.org/dc/terms/">
  
  <dcterms:title>
	Letter from Bruch, Charles Patterson to Mallory, Walter Seeley, April 06, 1905
  </dcterms:title>
  <dcterms:date>
	1905-04-06
  </dcterms:date>
  <dcterms:creator>
  	Bruch, Charles Patterson
  </dcterms:creator>
  <dcterms:contributor>
	Mallory, Walter Seeley
  </dcterms:contributor>
  <dcterms:subject>
	Edison, Mina Miller (Mrs Thomas A.); Edison, Thomas Alva; Magnetic Club; Postal Telegraph Cable Co; Awards & honors/clubs & societies; TAE friends and associates; Telegraph
  </dcterms:subject>   
  <dcterms:publisher>
	The Thomas Edison Papers, part of The School of Arts and Sciences at Rutgers, The State University of New Jersey
  </dcterms:publisher>
  <dcterms:source>
	Courtesy of Thomas Edison National Historical Park.
  </dcterms:source>
  <dcterms:identifier>
	D0509AAA2
  </dcterms:identifier>
	<dcterms:identifier>
		TAEM 190:20
	</dcterms:identifier>
  <dcterms:isPartOf>
	[D0509] Document File Series -- 1905 (D-05-09) Edison, T.A. -- Clubs &amp; Societies
  </dcterms:isPartOf> 
  <dcterms:isPartOf type="dcterms:URI">
	http://edison.rutgers.edu/NamesSearch/glocpage.php?gloc=D0509
  </dcterms:isPartOf>none available
</metadata>
